<?xml version='1.0' encoding='utf-8'?>
<TextureAtlas imagePath="NymSam_Duo.png">
<SubTexture name="spooky dance idle0000" x="0" y="0" width="333" height="866" frameX="-275" frameY="-187" frameWidth="780" frameHeight="1083"/>
<SubTexture name="spooky dance idle0001" x="0" y="0" width="333" height="866" frameX="-275" frameY="-187" frameWidth="780" frameHeight="1083"/>
<SubTexture name="spooky dance idle0002" x="333" y="0" width="332" height="864" frameX="-275" frameY="-188" frameWidth="780" frameHeight="1083"/>
<SubTexture name="spooky dance idle0003" x="333" y="0" width="332" height="864" frameX="-275" frameY="-188" frameWidth="780" frameHeight="1083"/>
<SubTexture name="spooky dance idle0004" x="665" y="0" width="290" height="604" frameX="-250" frameY="-448" frameWidth="780" frameHeight="1083"/>
<SubTexture name="spooky dance idle0005" x="665" y="0" width="290" height="604" frameX="-250" frameY="-448" frameWidth="780" frameHeight="1083"/>
<SubTexture name="spooky dance idle0006" x="955" y="0" width="287" height="608" frameX="-252" frameY="-442" frameWidth="780" frameHeight="1083"/>
<SubTexture name="spooky dance idle0007" x="955" y="0" width="287" height="608" frameX="-252" frameY="-442" frameWidth="780" frameHeight="1083"/>
<SubTexture name="spooky dance idle0008" x="1242" y="0" width="344" height="869" frameX="-207" frameY="-187" frameWidth="780" frameHeight="1083"/>
<SubTexture name="spooky dance idle0009" x="1242" y="0" width="344" height="869" frameX="-207" frameY="-187" frameWidth="780" frameHeight="1083"/>
<SubTexture name="spooky dance idle0010" x="1586" y="0" width="338" height="864" frameX="-208" frameY="-188" frameWidth="780" frameHeight="1083"/>
<SubTexture name="spooky dance idle0011" x="1586" y="0" width="338" height="864" frameX="-208" frameY="-188" frameWidth="780" frameHeight="1083"/>
<SubTexture name="spooky dance idle0012" x="665" y="0" width="290" height="604" frameX="-250" frameY="-448" frameWidth="780" frameHeight="1083"/>
<SubTexture name="spooky dance idle0013" x="665" y="0" width="290" height="604" frameX="-250" frameY="-448" frameWidth="780" frameHeight="1083"/>
<SubTexture name="spooky dance idle0014" x="955" y="0" width="287" height="608" frameX="-252" frameY="-442" frameWidth="780" frameHeight="1083"/>
<SubTexture name="spooky dance idle0015" x="955" y="0" width="287" height="608" frameX="-252" frameY="-442" frameWidth="780" frameHeight="1083"/>
<SubTexture name="note sing left0000" x="0" y="869" width="526" height="824" frameX="-53" frameY="-230" frameWidth="780" frameHeight="1083"/>
<SubTexture name="note sing left0001" x="0" y="869" width="526" height="824" frameX="-53" frameY="-230" frameWidth="780" frameHeight="1083"/>
<SubTexture name="note sing left0002" x="526" y="869" width="529" height="826" frameX="-55" frameY="-226" frameWidth="780" frameHeight="1083"/>
<SubTexture name="note sing left0003" x="526" y="869" width="529" height="826" frameX="-55" frameY="-226" frameWidth="780" frameHeight="1083"/>
<SubTexture name="note sing left0004" x="1055" y="869" width="529" height="826" frameX="-55" frameY="-226" frameWidth="780" frameHeight="1083"/>
<SubTexture name="note sing left0005" x="1055" y="869" width="529" height="826" frameX="-55" frameY="-226" frameWidth="780" frameHeight="1083"/>
<SubTexture name="note sing left0006" x="1055" y="869" width="529" height="826" frameX="-55" frameY="-226" frameWidth="780" frameHeight="1083"/>
<SubTexture name="note sing left0007" x="1055" y="869" width="529" height="826" frameX="-55" frameY="-226" frameWidth="780" frameHeight="1083"/>
<SubTexture name="note sing left0008" x="1055" y="869" width="529" height="826" frameX="-55" frameY="-226" frameWidth="780" frameHeight="1083"/>
<SubTexture name="note sing left0009" x="1055" y="869" width="529" height="826" frameX="-55" frameY="-226" frameWidth="780" frameHeight="1083"/>
<SubTexture name="note sing left0010" x="1055" y="869" width="529" height="826" frameX="-55" frameY="-226" frameWidth="780" frameHeight="1083"/>
<SubTexture name="note sing left0011" x="1055" y="869" width="529" height="826" frameX="-55" frameY="-226" frameWidth="780" frameHeight="1083"/>
<SubTexture name="note sing left0012" x="1055" y="869" width="529" height="826" frameX="-55" frameY="-226" frameWidth="780" frameHeight="1083"/>
<SubTexture name="note sing left0013" x="1055" y="869" width="529" height="826" frameX="-55" frameY="-226" frameWidth="780" frameHeight="1083"/>
<SubTexture name="spooky DOWN note0000" x="1584" y="869" width="378" height="581" frameX="-181" frameY="-473" frameWidth="780" frameHeight="1083"/>
<SubTexture name="spooky DOWN note0001" x="1584" y="869" width="378" height="581" frameX="-181" frameY="-473" frameWidth="780" frameHeight="1083"/>
<SubTexture name="spooky DOWN note0002" x="1962" y="869" width="371" height="592" frameX="-182" frameY="-460" frameWidth="780" frameHeight="1083"/>
<SubTexture name="spooky DOWN note0003" x="1962" y="869" width="371" height="592" frameX="-182" frameY="-460" frameWidth="780" frameHeight="1083"/>
<SubTexture name="spooky DOWN note0004" x="2333" y="869" width="371" height="592" frameX="-182" frameY="-460" frameWidth="780" frameHeight="1083"/>
<SubTexture name="spooky DOWN note0005" x="2333" y="869" width="371" height="592" frameX="-182" frameY="-460" frameWidth="780" frameHeight="1083"/>
<SubTexture name="spooky DOWN note0006" x="2333" y="869" width="371" height="592" frameX="-182" frameY="-460" frameWidth="780" frameHeight="1083"/>
<SubTexture name="spooky DOWN note0007" x="2333" y="869" width="371" height="592" frameX="-182" frameY="-460" frameWidth="780" frameHeight="1083"/>
<SubTexture name="spooky DOWN note0008" x="2333" y="869" width="371" height="592" frameX="-182" frameY="-460" frameWidth="780" frameHeight="1083"/>
<SubTexture name="spooky DOWN note0009" x="2333" y="869" width="371" height="592" frameX="-182" frameY="-460" frameWidth="780" frameHeight="1083"/>
<SubTexture name="spooky DOWN note0010" x="2333" y="869" width="371" height="592" frameX="-182" frameY="-460" frameWidth="780" frameHeight="1083"/>
<SubTexture name="spooky DOWN note0011" x="2333" y="869" width="371" height="592" frameX="-182" frameY="-460" frameWidth="780" frameHeight="1083"/>
<SubTexture name="spooky DOWN note0012" x="2333" y="869" width="371" height="592" frameX="-182" frameY="-460" frameWidth="780" frameHeight="1083"/>
<SubTexture name="spooky DOWN note0013" x="2333" y="869" width="371" height="592" frameX="-182" frameY="-460" frameWidth="780" frameHeight="1083"/>
<SubTexture name="spooky DOWN note0014" x="2333" y="869" width="371" height="592" frameX="-182" frameY="-460" frameWidth="780" frameHeight="1083"/>
<SubTexture name="spooky DOWN note0015" x="2333" y="869" width="371" height="592" frameX="-182" frameY="-460" frameWidth="780" frameHeight="1083"/>
<SubTexture name="spooky DOWN note0016" x="2333" y="869" width="371" height="592" frameX="-182" frameY="-460" frameWidth="780" frameHeight="1083"/>
<SubTexture name="spooky DOWN note0017" x="2333" y="869" width="371" height="592" frameX="-182" frameY="-460" frameWidth="780" frameHeight="1083"/>
<SubTexture name="spooky DOWN note0018" x="2333" y="869" width="371" height="592" frameX="-182" frameY="-460" frameWidth="780" frameHeight="1083"/>
<SubTexture name="spooky DOWN note0019" x="2333" y="869" width="371" height="592" frameX="-182" frameY="-460" frameWidth="780" frameHeight="1083"/>
<SubTexture name="spooky DOWN note0020" x="2333" y="869" width="371" height="592" frameX="-182" frameY="-460" frameWidth="780" frameHeight="1083"/>
<SubTexture name="spooky DOWN note0021" x="2333" y="869" width="371" height="592" frameX="-182" frameY="-460" frameWidth="780" frameHeight="1083"/>
<SubTexture name="spooky DOWN note0022" x="2333" y="869" width="371" height="592" frameX="-182" frameY="-460" frameWidth="780" frameHeight="1083"/>
<SubTexture name="spooky DOWN note0023" x="2333" y="869" width="371" height="592" frameX="-182" frameY="-460" frameWidth="780" frameHeight="1083"/>
<SubTexture name="spooky UP NOTE0000" x="0" y="1695" width="358" height="856" frameX="-171" frameY="-198" frameWidth="780" frameHeight="1083"/>
<SubTexture name="spooky UP NOTE0001" x="0" y="1695" width="358" height="856" frameX="-171" frameY="-198" frameWidth="780" frameHeight="1083"/>
<SubTexture name="spooky UP NOTE0002" x="358" y="1695" width="348" height="851" frameX="-180" frameY="-202" frameWidth="780" frameHeight="1083"/>
<SubTexture name="spooky UP NOTE0003" x="358" y="1695" width="348" height="851" frameX="-180" frameY="-202" frameWidth="780" frameHeight="1083"/>
<SubTexture name="spooky UP NOTE0004" x="706" y="1695" width="348" height="851" frameX="-180" frameY="-202" frameWidth="780" frameHeight="1083"/>
<SubTexture name="spooky UP NOTE0005" x="706" y="1695" width="348" height="851" frameX="-180" frameY="-202" frameWidth="780" frameHeight="1083"/>
<SubTexture name="spooky UP NOTE0006" x="706" y="1695" width="348" height="851" frameX="-180" frameY="-202" frameWidth="780" frameHeight="1083"/>
<SubTexture name="spooky UP NOTE0007" x="706" y="1695" width="348" height="851" frameX="-180" frameY="-202" frameWidth="780" frameHeight="1083"/>
<SubTexture name="spooky UP NOTE0008" x="706" y="1695" width="348" height="851" frameX="-180" frameY="-202" frameWidth="780" frameHeight="1083"/>
<SubTexture name="spooky UP NOTE0009" x="706" y="1695" width="348" height="851" frameX="-180" frameY="-202" frameWidth="780" frameHeight="1083"/>
<SubTexture name="spooky sing right0000" x="1054" y="1695" width="356" height="832" frameX="-248" frameY="-220" frameWidth="780" frameHeight="1083"/>
<SubTexture name="spooky sing right0001" x="1054" y="1695" width="356" height="832" frameX="-248" frameY="-220" frameWidth="780" frameHeight="1083"/>
<SubTexture name="spooky sing right0002" x="1410" y="1695" width="363" height="834" frameX="-243" frameY="-218" frameWidth="780" frameHeight="1083"/>
<SubTexture name="spooky sing right0003" x="1410" y="1695" width="363" height="834" frameX="-243" frameY="-218" frameWidth="780" frameHeight="1083"/>
<SubTexture name="spooky sing right0004" x="1773" y="1695" width="363" height="834" frameX="-243" frameY="-218" frameWidth="780" frameHeight="1083"/>
<SubTexture name="spooky sing right0005" x="1773" y="1695" width="363" height="834" frameX="-243" frameY="-218" frameWidth="780" frameHeight="1083"/>
<SubTexture name="spooky sing right0006" x="1773" y="1695" width="363" height="834" frameX="-243" frameY="-218" frameWidth="780" frameHeight="1083"/>
<SubTexture name="spooky sing right0007" x="1773" y="1695" width="363" height="834" frameX="-243" frameY="-218" frameWidth="780" frameHeight="1083"/>
<SubTexture name="spooky sing right0008" x="1773" y="1695" width="363" height="834" frameX="-243" frameY="-218" frameWidth="780" frameHeight="1083"/>
<SubTexture name="spooky sing right0009" x="1773" y="1695" width="363" height="834" frameX="-243" frameY="-218" frameWidth="780" frameHeight="1083"/>
<SubTexture name="spooky sing right0010" x="1773" y="1695" width="363" height="834" frameX="-243" frameY="-218" frameWidth="780" frameHeight="1083"/>
<SubTexture name="spooky sing right0011" x="1773" y="1695" width="363" height="834" frameX="-243" frameY="-218" frameWidth="780" frameHeight="1083"/>
<SubTexture name="spooky sing right0012" x="1773" y="1695" width="363" height="834" frameX="-243" frameY="-218" frameWidth="780" frameHeight="1083"/>
<SubTexture name="spooky sing right0013" x="1773" y="1695" width="363" height="834" frameX="-243" frameY="-218" frameWidth="780" frameHeight="1083"/>
<SubTexture name="spooky sing right0014" x="1773" y="1695" width="363" height="834" frameX="-243" frameY="-218" frameWidth="780" frameHeight="1083"/>
<SubTexture name="spooky sing right0015" x="1773" y="1695" width="363" height="834" frameX="-243" frameY="-218" frameWidth="780" frameHeight="1083"/>
<SubTexture name="spooky sing right0016" x="1773" y="1695" width="363" height="834" frameX="-243" frameY="-218" frameWidth="780" frameHeight="1083"/>
<SubTexture name="spooky sing right0017" x="1773" y="1695" width="363" height="834" frameX="-243" frameY="-218" frameWidth="780" frameHeight="1083"/>
<SubTexture name="spooky sing right0018" x="1773" y="1695" width="363" height="834" frameX="-243" frameY="-218" frameWidth="780" frameHeight="1083"/>
<SubTexture name="spooky sing right0019" x="1773" y="1695" width="363" height="834" frameX="-243" frameY="-218" frameWidth="780" frameHeight="1083"/>
<SubTexture name="spooky sing right0020" x="1773" y="1695" width="363" height="834" frameX="-243" frameY="-218" frameWidth="780" frameHeight="1083"/>
<SubTexture name="spooky sing right0021" x="1773" y="1695" width="363" height="834" frameX="-243" frameY="-218" frameWidth="780" frameHeight="1083"/>
<SubTexture name="spooky sing right0022" x="1773" y="1695" width="363" height="834" frameX="-243" frameY="-218" frameWidth="780" frameHeight="1083"/>
<SubTexture name="spooky sing right0023" x="1773" y="1695" width="363" height="834" frameX="-243" frameY="-218" frameWidth="780" frameHeight="1083"/>
</TextureAtlas>
